zebepy/__init__.py
zebepy-1.0.1.dist-info/METADATA
zebepy-1.0.1.dist-info/WHEEL
zebepy-1.0.1.dist-info/entry_points.txt
zebepy-1.0.1.dist-info/top_level.txt
zebepy-1.0.1.dist-info/RECORD
